pymacropad/__init__.py
pymacropad/__main__.py
pymacropad/config.py
pymacropad/daemon.py
pymacropad/default.yaml
pymacropad/macropad.py
pymacropad-1.2.2.dist-info/LICENSE
pymacropad-1.2.2.dist-info/METADATA
pymacropad-1.2.2.dist-info/WHEEL
pymacropad-1.2.2.dist-info/entry_points.txt
pymacropad-1.2.2.dist-info/top_level.txt
pymacropad-1.2.2.dist-info/RECORD
