Metadata-Version: 2.1
Name: pymacropad
Version: 1.2.2
Summary: Utility program for binding actions to keys on a given input
Home-page: https://github.com/j-waters/pymacropad
Author: James Waters
Author-email: james@jcwaters.co.uk
License: UNKNOWN
Platform: UNKNOWN
Requires-Python: >=3.10
License-File: LICENSE
Requires-Dist: PyYAML
Requires-Dist: Click
Requires-Dist: libevdev
Requires-Dist: pyxdg
